<?xml version="1.0" encoding="UTF-8"?>

<root-container name="activo_tramiteAprobacionInformeComercial" width="1220" height="566">
  <node name="inicio" x="0" y="0" width="132" height="36">
    <edge>
      <label x="5" y="-10"/>
    </edge>
  </node>
  <node name="T011_ComprobarDatos" x="0" y="0" width="132" height="36">
    <edge>
      <label x="5" y="-10"/>
    </edge>
    <edge>
      <label x="5" y="-10"/>
    </edge>
  </node>
  <node name="T011_RevisionInformeComercial" x="0" y="0" width="132" height="36">
    <edge>
      <label x="5" y="-10"/>
    </edge>
  </node>
  <node name="T011_RevisionInformeComercialDecision" x="0" y="0" width="132" height="36">
    <edge>
      <label x="5" y="-10"/>
    </edge>
    <edge>
      <label x="5" y="-10"/>
    </edge>
  </node>
  <node name="T011_AnalisisPeticionCorreccion" x="0" y="0" width="132" height="36">
    <edge>
      <label x="5" y="-10"/>
    </edge>
  </node>
  <node name="Fin" x="0" y="0" width="132" height="36"/>
</root-container>
